<?xml version="1.0" ?>
<song xmlns="http://openlyrics.info/namespace/2009/song" version="0.8">
  <properties>
    <titles>
      <title>Didn't I Walk On The Water</title>
    </titles>
    <authors>
      <author>Unbekannt</author>
    </authors>
    <verseOrder>v1</verseOrder>
  </properties>
  <lyrics>
    <verse name="v1">
      <lines>As I kneel in the darkness
In the middle of the night
I’m praying for assurance
Everything’s gonna be alright
Lord I see another battle
Out in front of me
I’m afraid I won’t be able
And I’ll go down in defeat</lines>
    </verse>
    <verse name="v2">
      <lines>And He said, didn't I walk on the water
And calmed the raging sea
I spoke to the wind,
It hushed and I gave you peace
Didn’t I run to your rescue
Didn’t I hear you when you called
I walked right beside you
Just so you wouldn’t fall
Didn’t I leave all of Heaven
Just to die for your sin
I searched until I found you
And I’d do it all again</lines>
    </verse>
    <verse name="v3">
      <lines>He said, do you remember
Where I brought you from
Just take a look behind you
At how far you’ve come
And everytime you asked me,
Didn’t I deliver you
So why would you be thinking
That I wouldn’t see you through</lines>
    </verse>
    <verse name="v4">
      <lines>Now she’s talking to her father
in a house that was once a home
She said my bills are coming due Lord
and six days is not that long
She hears a voice so still and low
It says I’ve moved like that before
And I’ll do this little thing
And I’ll give you so much more</lines>
    </verse>
  </lyrics>
</song>
