<?xml version="1.0" ?>
<song xmlns="http://openlyrics.info/namespace/2009/song" version="0.8">
  <properties>
    <titles>
      <title>Five Loaves and Two Fishes</title>
    </titles>
    <authors>
      <author>Unbekannt</author>
    </authors>
    <verseOrder>v1</verseOrder>
  </properties>
  <lyrics>
    <verse name="v1">
      <lines>A little boy of thirteen was on his way to school
He heard a crowd of people laughing
And he went to take a look
Thousands were listening to the stories of one man
He spoke with such wisdom,
Even the kids could understand</lines>
    </verse>
    <verse name="v2">
      <lines>The hours passed so quickly,
The day turned into night
Everyone was hungry
But there was no food in sight
The boy looked in his lunchbox
At the little that he had
He wasn't sure what good it'd do,
There were thousands to be fed</lines>
    </verse>
    <verse name="v3">
      <lines>But he saw the twinkling eyes of Jesus
The kindness in His smile
And the boy cried out
With the trust of a child
He said:</lines>
    </verse>
    <verse name="v4">
      <lines>&quot;Take my five loaves and two fishes
Do with it as you will
I surrender
Take my fears and my inhibitions
All my burdens, my ambitions
You can use it all to feed them all&quot;</lines>
    </verse>
    <verse name="v5">
      <lines>I often think about that boy
When I'm feeling small
And I worry that the work I do
Means nothing at all</lines>
    </verse>
    <verse name="v6">
      <lines>But every single tear I cry
Is a diamond in His hands
And every door that slams in my face,
I will offer up in prayer</lines>
    </verse>
    <verse name="v7">
      <lines>So I'll give you every breath that I have
Oh Lord, you can work miracles
All that you need is my &quot;Amen&quot;</lines>
    </verse>
    <verse name="v8">
      <lines>So take my five loaves and two fishes
Do with it as you will
I surrender
Take my fears and my inhibitions
All my burdens, my ambitions
You can use it all
I hope it's not too small</lines>
    </verse>
    <verse name="v9">
      <lines>I trust in you
I trust in you</lines>
    </verse>
    <verse name="v10">
      <lines>So take my five loaves and two fishes
Do with it as you will
I surrender
Take my fears and my inhibitions
All my burdens, my ambitions
You can use it all
No gift is too small</lines>
    </verse>
  </lyrics>
</song>
