<?xml version="1.0" ?>
<song xmlns="http://openlyrics.info/namespace/2009/song" version="0.8">
  <properties>
    <titles>
      <title>Greater</title>
    </titles>
    <authors>
      <author type="words">Jay Cook</author>
      <author type="music">Jay Cook</author>
    </authors>
    <verseOrder>v1 v2 v3 v4 v5 v6 v7 v8 v9 v10 v11 v12 v13 v14 v15 v16 v17 v18 v19 v20 v21 v22 v23</verseOrder>
  </properties>
  <lyrics>
    <verse name="v1">
      <lines>Almighty Savior
You never fail
You hold all power</lines>
    </verse>
    <verse name="v2">
      <lines>There's never a challenge
Or a need to worry
We always win</lines>
    </verse>
    <verse name="v3">
      <lines>You're great
And there's no one like You
You're true
And none compare to You</lines>
    </verse>
    <verse name="v4">
      <lines>Great
And there's no one like You
You're never ending
Never ending
Great</lines>
    </verse>
    <verse name="v5">
      <lines>Almighty Savior
You never fail
You hold all power</lines>
    </verse>
    <verse name="v6">
      <lines>There's never a challenge
Or a need to worry
We always win</lines>
    </verse>
    <verse name="v7">
      <lines>Because You're great
And there's no one like you
You're true
And none compare to You</lines>
    </verse>
    <verse name="v8">
      <lines>Great
And there's no one like You
You're never ending
Never ending</lines>
    </verse>
    <verse name="v9">
      <lines>You're great
And there's no one like You
You're true
And none compare to You</lines>
    </verse>
    <verse name="v10">
      <lines>Great
And there's no one like You
You're never ending
Never ending</lines>
    </verse>
    <verse name="v11">
      <lines>No sickness is stronger than You
No power is greater than You
No wisdom is wiser than You
You're greater
You're greater</lines>
    </verse>
    <verse name="v12">
      <lines>No sickness is stronger than You
No power is greater than You
No wisdom is wiser than You
You're greater
You're greater</lines>
    </verse>
    <verse name="v13">
      <lines>Greater
Greater
Greater
No one compares
For you are</lines>
    </verse>
    <verse name="v14">
      <lines>Stronger
Stronger
You're greater
Greater</lines>
    </verse>
    <verse name="v15">
      <lines>Our God is greater
Our God is stronger
God you are higher than any other</lines>
    </verse>
    <verse name="v16">
      <lines>Our God is Healer
Awesome in Power
Our God
Our God</lines>
    </verse>
    <verse name="v17">
      <lines>Our God is greater
Our God is stronger
God you are higher than any other</lines>
    </verse>
    <verse name="v18">
      <lines>Our God is Healer
Awesome in Power
Our God
Our God</lines>
    </verse>
    <verse name="v19">
      <lines>And if our God is for us
Then who could ever stop us?
And if our God is with us
Then what can stand against?</lines>
    </verse>
    <verse name="v20">
      <lines>And if our God is for us
Then who could ever stop us?
And if our God is with us
Then what can stand against?</lines>
    </verse>
    <verse name="v21">
      <lines>Then what can stand against?</lines>
    </verse>
    <verse name="v22">
      <lines>No sickness is stronger than You
No power is greater than You
No wisdom is wiser than You
You're greater
You're greater</lines>
    </verse>
    <verse name="v23">
      <lines>No sickness is stronger than You
No power is greater than You
No wisdom is wiser than You
You're greater
You're greater</lines>
    </verse>
  </lyrics>
</song>
