<?xml version="1.0" ?>
<song xmlns="http://openlyrics.info/namespace/2009/song" version="0.8">
  <properties>
    <titles>
      <title>What Could be Better</title>
    </titles>
    <authors>
      <author>Unbekannt</author>
    </authors>
    <verseOrder>v1 v2 v3 v4 v5 v6 v7 v8 v9 v10 v11 v12</verseOrder>
  </properties>
  <lyrics>
    <verse name="v1">
      <lines>I've heard it said today is all we're given
Tomorrow may not come so you better start living
I guess it all depends on your point of view, yeah yeah</lines>
    </verse>
    <verse name="v2">
      <lines>Well, pardon me if I, I just don't listen
To everything the world says I'm missing
There's nothing here and now I'm gonna hold on to, hold on to</lines>
    </verse>
    <verse name="v3">
      <lines>Now I'm living in the days ahead
I'm already dancing on the streets of gold
And I can't stop celebrating in my soul
'Cause I'm, I'm living in the days ahead
Nothing on earth could ever compare
I can't wait for the day that I get there</lines>
    </verse>
    <verse name="v4">
      <lines>When I see Jesus face to face
Tell me what could be better
Tell me what could be better, oh yeah yeah</lines>
    </verse>
    <verse name="v5">
      <lines>If home is where the heart is, then I'm in Heaven
It's the promise of tomorrow that I've been given
And who is waiting there I am living for, yeah yeah</lines>
    </verse>
    <verse name="v6">
      <lines>He's everything I love and I believe in
And I can hardly wait just to see Him
And hear Him say, Well done, I couldn't ask for more</lines>
    </verse>
    <verse name="v7">
      <lines>I'm singing now I'm living in the days ahead
I'm already dancing on the streets of gold
And I can't stop celebrating in my soul
'Cause I'm, I'm living in the days ahead
Nothing on earth could ever compare
I can't wait for the day that I get there</lines>
    </verse>
    <verse name="v8">
      <lines>When I see Jesus face to face
Tell me what could be better
What could be better, yeah</lines>
    </verse>
    <verse name="v9">
      <lines>Well, life is full of ups and downs
Inside outs, round and rounds
You can't blame me for dreaming about it, yeah yeah</lines>
    </verse>
    <verse name="v10">
      <lines>Now I'm, I'm living in the days ahead
I'm already dancing on the streets of gold
And I can't stop celebrating in my soul
'Cause I'm, I'm living in the days ahead
Nothing on earth could ever compare
I can't wait for the day that I get there</lines>
    </verse>
    <verse name="v11">
      <lines>When I see Jesus face to face
Yeah, when I see Jesus face to face
What could be better, yeah yeah yeah yeah</lines>
    </verse>
    <verse name="v12">
      <lines>What could be better
What could be better
What could be, what could be better
What could be better</lines>
    </verse>
  </lyrics>
</song>
