<?xml version='1.0' encoding='utf-8'?>
<song xmlns="http://openlyrics.info/namespace/2009/song" version="0.8" createdIn="OpenLP 3.1.0rc4" modifiedIn="OpenLP 3.1.0rc4" modifiedDate="2025-10-18T18:52:33"><properties><titles><title>Du Morgenstern, du Licht vom Licht</title></titles><authors><author type="words">Johann Gottfried Herder (1795), Richard Adelbert Lipsius (1878)</author></authors></properties><lyrics><verse name="V1"><lines>1)&lt;br/&gt;
 Du Morgenstern, du Licht vom Licht,&lt;br/&gt;
&lt;br/&gt;
das durch die Finsternisse bricht,&lt;br/&gt;
&lt;br/&gt;
du gingst vor aller Zeiten Lauf&lt;br/&gt;
&lt;br/&gt;
in unerschaffner Klarheit auf.</lines></verse><verse name="V2"><lines>Du Lebensquell, wir danken dir,&lt;br/&gt;
&lt;br/&gt;
auf dich, Lebend'ger, hoffen wir;&lt;br/&gt;
&lt;br/&gt;
denn du durchdrangst des Todes Nacht,&lt;br/&gt;
&lt;br/&gt;
hast Sieg und Leben uns gebracht.</lines></verse><verse name="V3"><lines>Du ew'ge Wahrheit, Gottes Bild,&lt;br/&gt;
&lt;br/&gt;
der du den Vater uns enthüllt,&lt;br/&gt;
&lt;br/&gt;
du kamst herab ins Erdental&lt;br/&gt;
&lt;br/&gt;
mit deiner Gotterkenntnis Strahl.</lines></verse><verse name="V4"><lines>Bleib bei uns, Herr, verlass uns nicht,&lt;br/&gt;
&lt;br/&gt;
führ uns durch Finsternis zum Licht,&lt;br/&gt;
&lt;br/&gt;
bleib auch am Abend dieser Welt&lt;br/&gt;
&lt;br/&gt;
als Hilf und Hort uns zugesellt.&lt;br/&gt;
&lt;br/&gt;
Die weihnachtliche Lichtsymbolik verbindet sich mit den Idealen der Aufklärung, des „siècle des lumières“: Klarheit, Erkenntnis, Wahrheit. Es ist aber zugleich das Osterlicht, das hier in die Welt scheint – die Erleuchtung ist ein Vorschein der Ewigkeit. Die Melodie stammt von einem alten Lied, das ebenfalls Christus als den Morgenstern besingt. &lt;br/&gt;
(&lt;br/&gt;
Andreas Marti&lt;br/&gt;
)</lines></verse></lyrics></song>