<?xml version='1.0' encoding='utf-8'?>
<song xmlns="http://openlyrics.info/namespace/2009/song" version="0.8" createdIn="OpenLP 3.1.0rc4" modifiedIn="OpenLP 3.1.0rc4" modifiedDate="2025-10-18T18:47:31"><properties><titles><title>Freuet euch, ihr Christen alle</title></titles><authors><author type="words">Christian Keimann (1645)</author></authors></properties><lyrics><verse name="V1"><lines>1) &lt;br/&gt;
 Freuet euch, ihr Christen alle,&lt;br/&gt;
&lt;br/&gt;
freue sich, wer immer kann;&lt;br/&gt;
&lt;br/&gt;
Gott hat viel an uns getan.&lt;br/&gt;
&lt;br/&gt;
Freuet euch mit großem Schalle,&lt;br/&gt;
&lt;br/&gt;
dass er uns so hochgeacht,&lt;br/&gt;
&lt;br/&gt;
sich mit uns befreundt gemacht.&lt;br/&gt;
&lt;br/&gt;
Ref.: &lt;br/&gt;
 Freude, Freude über Freude:&lt;br/&gt;
&lt;br/&gt;
Christus wehret allem Leide.&lt;br/&gt;
&lt;br/&gt;
Wonne, Wonne über Wonne:&lt;br/&gt;
&lt;br/&gt;
Christus ist die Gnadensonne.</lines></verse><verse name="V2"><lines>Siehe, siehe, meine Seele,&lt;br/&gt;
&lt;br/&gt;
wie dein Heiland kommt zu dir,&lt;br/&gt;
&lt;br/&gt;
brennt in Liebe für und für,&lt;br/&gt;
&lt;br/&gt;
dass er in der Krippen Höhle&lt;br/&gt;
&lt;br/&gt;
harte lieget dir zugut,&lt;br/&gt;
&lt;br/&gt;
dich zu lösen durch sein Blut.</lines></verse><verse name="V3"><lines>Jesu, wie soll ich dir danken?&lt;br/&gt;
&lt;br/&gt;
Ich bekenne, dass von dir&lt;br/&gt;
&lt;br/&gt;
meine Seligkeit herrührt.&lt;br/&gt;
&lt;br/&gt;
So lass mich von dir nicht wanken,&lt;br/&gt;
&lt;br/&gt;
nimm mich dir zu eigen hin,&lt;br/&gt;
&lt;br/&gt;
so empfindet Herz und Sinn.</lines></verse><verse name="V4"><lines>Jesu, nimm dich deiner Glieder&lt;br/&gt;
&lt;br/&gt;
ferner noch in Gnaden an;&lt;br/&gt;
&lt;br/&gt;
schenke, was man bitten kann,&lt;br/&gt;
&lt;br/&gt;
zu erquicken deine Brüder;&lt;br/&gt;
&lt;br/&gt;
gib der ganzen Christenschar&lt;br/&gt;
&lt;br/&gt;
Frieden und ein seligs Jahr.</lines></verse></lyrics></song>