<?xml version='1.0' encoding='utf-8'?>
<song xmlns="http://openlyrics.info/namespace/2009/song" version="0.8" createdIn="OpenLP 3.1.0rc4" modifiedIn="OpenLP 3.1.0rc4" modifiedDate="2025-10-18T19:06:29"><properties><titles><title>Gib Frieden, Herr, gib Frieden</title></titles><authors><author type="words">Jürgen Henkys (1983)</author></authors></properties><lyrics><verse name="V1"><lines>Nach dem niederländischen „Greev vrede, Heer, geef vrede” von Jan Nooter 1963.&lt;br/&gt;
&lt;br/&gt;
"Gib Frieden, Herr, gib Frieden" ist ein von dem mennonitischen Kirchenlieddichter Jan Nooter verfasstes Kirchenlied. Das Gebetslied mit seiner Bitte um Frieden findet sich heute in vielen christlichen Gesangbüchern.&lt;br/&gt;
&lt;br/&gt;
In der Tradition der alttestamentlichen Klagepsalmen wird hier das Unrecht der Welt vor Gott gebracht – Machtmissbrauch, Lüge, Gewalt, Furcht. Es überwinden zu können, ist Gottes Gabe und zugleich unsere Aufgabe, weil er uns die Kraft schenkt zur Feindesliebe, zum Händereichen, zur Wahrheit, zum Leben als Friedenszeichen. &lt;br/&gt;
(&lt;br/&gt;
Andreas Marti&lt;br/&gt;
)</lines></verse></lyrics></song>